vectara_speech/MarkoBits.py
vectara_speech/__init__.py
vectara_speech/render.py
vectara_speech/speech.py
vectara_speech_helper-0.0.5.dist-info/LICENSE.md
vectara_speech_helper-0.0.5.dist-info/METADATA
vectara_speech_helper-0.0.5.dist-info/WHEEL
vectara_speech_helper-0.0.5.dist-info/top_level.txt
vectara_speech_helper-0.0.5.dist-info/RECORD
