Metadata-Version: 2.1
Name: vectara-speech-helper
Version: 0.0.5
Summary: Vectara Speech Helper
Home-page: https://github.com/davidglevy/vectara-speech-helper
Author: David Levy
Author-email: david.g.levy@gmail.com
License: GNU AFFERO GENERAL PUBLIC LICENSE v3
Classifier: Development Status :: 2 - Pre-Alpha
Classifier: Environment :: Console
Classifier: License :: OSI Approved :: GNU Affero General Public License v3 or later (AGPLv3+)
Classifier: Natural Language :: English
Classifier: Programming Language :: Python :: 3 :: Only
Classifier: Programming Language :: Python :: 3.12
Classifier: Topic :: Utilities
Requires-Python: >=3.12
License-File: LICENSE.md
Requires-Dist: vectara-skunk-client >=0.4.14
Requires-Dist: marko ==2.0.2
Requires-Dist: python-docx >=1.1.0
Requires-Dist: Jinja2 ==3.1.3
